azure_api/__init__.py
azure_api/azure_api.py
gerswin_azure_api_rest-1.0.2.dist-info/METADATA
gerswin_azure_api_rest-1.0.2.dist-info/WHEEL
gerswin_azure_api_rest-1.0.2.dist-info/top_level.txt
gerswin_azure_api_rest-1.0.2.dist-info/RECORD
