Metadata-Version: 2.1
Name: gerswin-azure-api-rest
Version: 1.0.2
Summary: Python azure short api
Home-page: UNKNOWN
Author: Gerswin Pineda
Author-email: g3rswin@gmail.com
License: UNKNOWN
Keywords: python,azuredevops,azure
Platform: UNKNOWN
Classifier: Development Status :: 3 - Alpha
Classifier: Intended Audience :: Developers
Classifier: Programming Language :: Python :: 3
Classifier: Topic :: Software Development :: Libraries :: Python Modules
Classifier: Topic :: Software Development :: Libraries
Classifier: License :: OSI Approved :: MIT License
Requires-Dist: requests
